{
  "schema_version": "1.0",
  "engine": "sce",
  "managed": true,
  "last_aligned_sce_version": "3.4.0",
  "defaults": {
    "autonomous": {
      "enabled": true,
      "mode": "aggressive",
      "require_step_confirmation": false,
      "apply_all_work_by_default": true
    },
    "session_governance": {
      "scene_primary_session_required": true,
      "one_scene_one_primary_session": true,
      "spec_runs_bind_child_session": true,
      "scene_completion_auto_rollover": true
    },
    "spec_domain_policy": {
      "closed_loop_research_required": true,
      "coverage_validation_required": true,
      "fail_on_gap_default": true
    },
    "debug_policy": {
      "prioritize_root_cause_fix": true,
      "max_direct_fix_rounds_before_debug": 2,
      "forbid_bypass_workarounds": true
    },
    "migration_policy": {
      "legacy_kiro_supported": false,
      "require_manual_legacy_migration_confirmation": true
    }
  }
}
